[{"message":"**Sinatra (citizenid: VGL78135 | id: 1)** $10 (bank) added, new bank balance: 5020 reason: unknown","from":"playermoney","time":1682471932,"title":"AddMoney"},{"message":"**Sinatra (citizenid: VGL78135 | id: 1)** $10 (bank) added, new bank balance: 5030 reason: unknown","from":"playermoney","time":1682472532,"title":"AddMoney"},{"message":"**Sinatra (citizenid: VGL78135 | id: 1)** $10 (bank) added, new bank balance: 5040 reason: unknown","from":"playermoney","time":1682473132,"title":"AddMoney"},{"message":"**Sinatra (citizenid: VGL78135 | id: 1)** $10 (bank) added, new bank balance: 5070 reason: unknown","from":"playermoney","time":1684178246,"title":"AddMoney"},{"message":"**Sinatra (citizenid: VGL78135 | id: 1)** $10 (bank) added, new bank balance: 5080 reason: unknown","from":"playermoney","time":1684178846,"title":"AddMoney"},{"message":"**Sinatra (citizenid: VGL78135 | id: 1)** $10 (bank) added, new bank balance: 5090 reason: unknown","from":"playermoney","time":1684179446,"title":"AddMoney"},{"message":"**Sinatra** (license:773796cbecdfa2323ecd202751eb382b775451d6) left..\n **Reason:** You were kicked for being AFK","from":"joinleave","time":1684179535,"title":"Dropped"},{"message":"**Sinatra** (<@796652367797157948> |  ||ip:192.168.219.7|| | license:773796cbecdfa2323ecd202751eb382b775451d6 | VGL78135 | 2) loaded..","from":"joinleave","time":1684179640,"title":"Loaded"},{"message":"**Sinatra (citizenid: VGL78135 | id: 2)** $10 (bank) added, new bank balance: 5100 reason: unknown","from":"playermoney","time":1684180046,"title":"AddMoney"},{"message":"**Sinatra (citizenid: VGL78135 | id: 2)** $10 (bank) added, new bank balance: 5110 reason: unknown","from":"playermoney","time":1684180646,"title":"AddMoney"},{"message":"**Sinatra (citizenid: VGL78135 | id: 2)** $10 (bank) added, new bank balance: 5120 reason: unknown","from":"playermoney","time":1684181246,"title":"AddMoney"},{"message":"**Invalid** (0) has killed Sinatra (2) with a **Fall** (weapon_fall)","from":"death","time":1684181548,"title":"Sinatra (2) (2) is dead"},{"message":"**Sinatra (citizenid: VGL78135 | id: 2)** $10 (bank) added, new bank balance: 5130 reason: unknown","from":"playermoney","time":1684181846,"title":"AddMoney"},{"message":"**Steve Macdonald (citizenid: WUP87052 | id: 1)** items set: [{\"name\":\"vehiclekey\",\"amount\":1,\"label\":\"Clée de Voiture\",\"description\":\" \",\"unique\":true,\"image\":\"vehiclekey.png\",\"weight\":10,\"type\":\"item\",\"useable\":false,\"slot\":1,\"info\":{\"plate\":\"26BKQ289\",\"lock\":4322,\"model\":\"Ubermacht Drift Cypher\"},\"shouldClose\":false},{\"name\":\"vehiclekey\",\"amount\":1,\"label\":\"Clée de Voiture\",\"description\":\" \",\"unique\":true,\"image\":\"vehiclekey.png\",\"weight\":10,\"type\":\"item\",\"useable\":false,\"slot\":2,\"info\":{\"plate\":\"2EF294VM\",\"lock\":4322,\"model\":\"Western Wolfsbane\"},\"shouldClose\":false},{\"name\":\"pokemonbox\",\"amount\":1,\"label\":\"Classeur Pokémon\",\"description\":\"Classeur Pokémon\",\"unique\":true,\"image\":\"pokemonbox.png\",\"weight\":500,\"type\":\"item\",\"useable\":true,\"slot\":3,\"info\":{\"inventory_id\":\"Pokemonbox_68827\",\"label\":\"Boîte Pokémon de WUP87052\"},\"shouldClose\":false},{\"name\":\"booster151\",\"amount\":1,\"label\":\"booster 151\",\"unique\":false,\"image\":\"booster151.png\",\"description\":\"booster     \",\"type\":\"item\",\"useable\":true,\"slot\":4,\"weight\":0,\"info\":[]},{\"name\":\"bank_card\",\"amount\":1,\"label\":\"Carte Bleu\",\"description\":\"Used to access ATM\",\"unique\":true,\"image\":\"bank_card.png\",\"weight\":0,\"type\":\"item\",\"useable\":true,\"slot\":5,\"info\":{\"name\":\"Steve Macdonald\",\"cardNumber\":3012276324109522,\"citizenid\":\"WUP87052\",\"cardPin\":1911},\"shouldClose\":true},{\"name\":\"green_phone\",\"amount\":1,\"label\":\"Iphone Vert \",\"description\":\"They say that Quasar Smartphone is the same as an iPhone, what do you think?\",\"unique\":true,\"image\":\"green_phone.png\",\"weight\":700,\"type\":\"item\",\"useable\":true,\"slot\":6,\"info\":[],\"shouldClose\":true},{\"name\":\"cash\",\"amount\":3232,\"label\":\"Cash $\",\"description\":\"Tu a le droit a 10000€ sur toi\",\"unique\":false,\"image\":\"cash.png\",\"weight\":0,\"type\":\"item\",\"useable\":false,\"slot\":7,\"info\":[],\"shouldClose\":true},{\"name\":\"sandwich\",\"amount\":66,\"label\":\"Sandwich\",\"description\":\"Nice bread for your stomach\",\"unique\":false,\"image\":\"sandwich.png\",\"weight\":200,\"type\":\"item\",\"useable\":true,\"slot\":8,\"info\":[],\"shouldClose\":true},{\"name\":\"nitrous\",\"amount\":1,\"label\":\"Nitro\",\"description\":\"Speed up, gas pedal! :D\",\"unique\":false,\"image\":\"nitrous.png\",\"weight\":1000,\"type\":\"item\",\"useable\":true,\"slot\":9,\"info\":[],\"shouldClose\":true},{\"name\":\"veh_armor\",\"amount\":1,\"label\":\"Armure\",\"description\":\"\",\"unique\":false,\"image\":\"veh_armor.png\",\"weight\":1000,\"type\":\"item\",\"useable\":true,\"slot\":10,\"info\":[],\"shouldClose\":true},{\"name\":\"vehiclekey\",\"amount\":1,\"label\":\"Clée de Voiture\",\"description\":\" \",\"unique\":true,\"image\":\"vehiclekey.png\",\"weight\":10,\"type\":\"item\",\"useable\":false,\"slot\":11,\"info\":{\"plate\":\"63GCQ354\",\"lock\":4322,\"model\":\"2008 BMW M3 e92\"},\"shouldClose\":false},{\"name\":\"black_money\",\"amount\":5000,\"label\":\"Argent Noir\",\"description\":\"\",\"unique\":false,\"image\":\"black_money.png\",\"weight\":0,\"type\":\"item\",\"useable\":false,\"slot\":12,\"info\":[],\"shouldClose\":true},{\"name\":\"harness\",\"amount\":1,\"label\":\"Harnais de course\",\"description\":\"Racing Harness so no matter what you stay in the car\",\"unique\":true,\"image\":\"harness.png\",\"weight\":1000,\"type\":\"item\",\"useable\":true,\"slot\":13,\"info\":{\"uses\":17},\"shouldClose\":true},{\"name\":\"driver_license\",\"amount\":1,\"label\":\"Permis de Conduire\",\"description\":\"Permit to show you can drive a vehicle\",\"unique\":true,\"image\":\"driver_license.png\",\"weight\":0,\"type\":\"item\",\"useable\":true,\"slot\":14,\"info\":{\"lastname\":\"Macdonald\",\"firstname\":\"Steve\",\"birthdate\":\"1991-11-19\",\"type\":\"A1-A2-A | AM-B | C1-C-CE\"},\"shouldClose\":true},{\"name\":\"boogeyman_pop\",\"amount\":2,\"label\":\"Boogeyman\",\"unique\":false,\"image\":\"boogeyman_pop.png\",\"description\":\"Pop Boogeyman\",\"type\":\"item\",\"useable\":true,\"slot\":15,\"weight\":10,\"info\":[]},{\"name\":\"empty_weed_bag\",\"amount\":4,\"label\":\"Pochon vide\",\"description\":\"A small empty bag\",\"unique\":false,\"image\":\"weed_baggy_empty.png\",\"weight\":10,\"type\":\"item\",\"useable\":true,\"slot\":16,\"info\":[],\"shouldClose\":true},{\"name\":\"petfood\",\"amount\":1,\"label\":\"Nourriture animaux\",\"unique\":false,\"image\":\"petfood.png\",\"description\":\"Pour nourrir votre animal\",\"type\":\"item\",\"useable\":true,\"slot\":17,\"weight\":10,\"info\":[]},{\"name\":\"tennisball\",\"amount\":1,\"label\":\"Balle de Tennis\",\"unique\":false,\"image\":\"tennisball.png\",\"description\":\"Pour votre animal\",\"type\":\"item\",\"useable\":true,\"slot\":18,\"weight\":10,\"info\":[]}]","from":"playerinventory","title":"SetInventory","time":1733072890},{"message":"**Steve Macdonald (citizenid: WUP87052 | id: 1)** items set: [{\"name\":\"vehiclekey\",\"amount\":1,\"label\":\"Clée de Voiture\",\"description\":\" \",\"unique\":true,\"image\":\"vehiclekey.png\",\"weight\":10,\"type\":\"item\",\"useable\":false,\"slot\":1,\"info\":{\"plate\":\"26BKQ289\",\"lock\":4322,\"model\":\"Ubermacht Drift Cypher\"},\"shouldClose\":false},{\"name\":\"vehiclekey\",\"amount\":1,\"label\":\"Clée de Voiture\",\"description\":\" \",\"unique\":true,\"image\":\"vehiclekey.png\",\"weight\":10,\"type\":\"item\",\"useable\":false,\"slot\":2,\"info\":{\"plate\":\"2EF294VM\",\"lock\":4322,\"model\":\"Western Wolfsbane\"},\"shouldClose\":false},{\"name\":\"pokemonbox\",\"amount\":1,\"label\":\"Classeur Pokémon\",\"description\":\"Classeur Pokémon\",\"unique\":true,\"image\":\"pokemonbox.png\",\"weight\":500,\"type\":\"item\",\"useable\":true,\"slot\":3,\"info\":{\"inventory_id\":\"Pokemonbox_68827\",\"label\":\"Boîte Pokémon de WUP87052\"},\"shouldClose\":false},{\"name\":\"booster151\",\"amount\":1,\"label\":\"booster 151\",\"unique\":false,\"image\":\"booster151.png\",\"description\":\"booster     \",\"type\":\"item\",\"useable\":true,\"slot\":4,\"weight\":0,\"info\":[]},{\"name\":\"bank_card\",\"amount\":1,\"label\":\"Carte Bleu\",\"description\":\"Used to access ATM\",\"unique\":true,\"image\":\"bank_card.png\",\"weight\":0,\"type\":\"item\",\"useable\":true,\"slot\":5,\"info\":{\"name\":\"Steve Macdonald\",\"cardNumber\":3012276324109522,\"citizenid\":\"WUP87052\",\"cardPin\":1911},\"shouldClose\":true},{\"name\":\"green_phone\",\"amount\":1,\"label\":\"Iphone Vert \",\"description\":\"They say that Quasar Smartphone is the same as an iPhone, what do you think?\",\"unique\":true,\"image\":\"green_phone.png\",\"weight\":700,\"type\":\"item\",\"useable\":true,\"slot\":6,\"info\":[],\"shouldClose\":true},{\"name\":\"cash\",\"amount\":3232,\"label\":\"Cash $\",\"description\":\"Tu a le droit a 10000€ sur toi\",\"unique\":false,\"image\":\"cash.png\",\"weight\":0,\"type\":\"item\",\"useable\":false,\"slot\":7,\"info\":[],\"shouldClose\":true},{\"name\":\"sandwich\",\"amount\":66,\"label\":\"Sandwich\",\"description\":\"Nice bread for your stomach\",\"unique\":false,\"image\":\"sandwich.png\",\"weight\":200,\"type\":\"item\",\"useable\":true,\"slot\":8,\"info\":[],\"shouldClose\":true},{\"name\":\"nitrous\",\"amount\":1,\"label\":\"Nitro\",\"description\":\"Speed up, gas pedal! :D\",\"unique\":false,\"image\":\"nitrous.png\",\"weight\":1000,\"type\":\"item\",\"useable\":true,\"slot\":9,\"info\":[],\"shouldClose\":true},{\"name\":\"veh_armor\",\"amount\":1,\"label\":\"Armure\",\"description\":\"\",\"unique\":false,\"image\":\"veh_armor.png\",\"weight\":1000,\"type\":\"item\",\"useable\":true,\"slot\":10,\"info\":[],\"shouldClose\":true},{\"name\":\"vehiclekey\",\"amount\":1,\"label\":\"Clée de Voiture\",\"description\":\" \",\"unique\":true,\"image\":\"vehiclekey.png\",\"weight\":10,\"type\":\"item\",\"useable\":false,\"slot\":11,\"info\":{\"plate\":\"63GCQ354\",\"lock\":4322,\"model\":\"2008 BMW M3 e92\"},\"shouldClose\":false},{\"name\":\"black_money\",\"amount\":5000,\"label\":\"Argent Noir\",\"description\":\"\",\"unique\":false,\"image\":\"black_money.png\",\"weight\":0,\"type\":\"item\",\"useable\":false,\"slot\":12,\"info\":[],\"shouldClose\":true},{\"name\":\"harness\",\"amount\":1,\"label\":\"Harnais de course\",\"description\":\"Racing Harness so no matter what you stay in the car\",\"unique\":true,\"image\":\"harness.png\",\"weight\":1000,\"type\":\"item\",\"useable\":true,\"slot\":13,\"info\":{\"uses\":17},\"shouldClose\":true},{\"name\":\"driver_license\",\"amount\":1,\"label\":\"Permis de Conduire\",\"description\":\"Permit to show you can drive a vehicle\",\"unique\":true,\"image\":\"driver_license.png\",\"weight\":0,\"type\":\"item\",\"useable\":true,\"slot\":14,\"info\":{\"lastname\":\"Macdonald\",\"firstname\":\"Steve\",\"birthdate\":\"1991-11-19\",\"type\":\"A1-A2-A | AM-B | C1-C-CE\"},\"shouldClose\":true},{\"name\":\"boogeyman_pop\",\"amount\":2,\"label\":\"Boogeyman\",\"unique\":false,\"image\":\"boogeyman_pop.png\",\"description\":\"Pop Boogeyman\",\"type\":\"item\",\"useable\":true,\"slot\":15,\"weight\":10,\"info\":[]},{\"name\":\"empty_weed_bag\",\"amount\":4,\"label\":\"Pochon vide\",\"description\":\"A small empty bag\",\"unique\":false,\"image\":\"weed_baggy_empty.png\",\"weight\":10,\"type\":\"item\",\"useable\":true,\"slot\":16,\"info\":[],\"shouldClose\":true},{\"name\":\"petfood\",\"amount\":1,\"label\":\"Nourriture animaux\",\"unique\":false,\"image\":\"petfood.png\",\"description\":\"Pour nourrir votre animal\",\"type\":\"item\",\"useable\":true,\"slot\":17,\"weight\":10,\"info\":[]},{\"name\":\"tennisball\",\"amount\":1,\"label\":\"Balle de Tennis\",\"unique\":false,\"image\":\"tennisball.png\",\"description\":\"Pour votre animal\",\"type\":\"item\",\"useable\":true,\"slot\":18,\"weight\":10,\"info\":[]}]","from":"playerinventory","title":"SetInventory","time":1733072890}]